MANIFEST.in
README.md
setup.py
hf_download/main.py
huggingface_download_cli.egg-info/PKG-INFO
huggingface_download_cli.egg-info/SOURCES.txt
huggingface_download_cli.egg-info/dependency_links.txt
huggingface_download_cli.egg-info/entry_points.txt
huggingface_download_cli.egg-info/top_level.txt