Metadata-Version: 2.1
Name: huggingface-download-cli
Version: 1.0.3
Summary: A utility to download files from the Hugging Face Model Hub
Author: xihajun
Author-email: junfan@krai.ai
